my_tiny_check_os_tools.cpython-310-darwin.so
zyn_py_pkg_test_2024_03_13-0.0.1.dist-info/METADATA
zyn_py_pkg_test_2024_03_13-0.0.1.dist-info/WHEEL
zyn_py_pkg_test_2024_03_13-0.0.1.dist-info/top_level.txt
zyn_py_pkg_test_2024_03_13-0.0.1.dist-info/RECORD
